rule34html/__init__.py
rule34html/cli.py
rule34html/client.py
rule34html/exceptions.py
rule34html/logger.py
rule34html/models.py
rule34html/utils.py
rule34html-0.1.1.dist-info/METADATA
rule34html-0.1.1.dist-info/WHEEL
rule34html-0.1.1.dist-info/entry_points.txt
rule34html-0.1.1.dist-info/top_level.txt
rule34html-0.1.1.dist-info/RECORD
