Metadata-Version: 2.4
Name: rule34html
Version: 0.1.1
Summary: Feature-rich HTML parser for rule34.xxx (no API). Search posts, autocomplete tags, get random images.
Author: Hotment
Requires-Python: >=3.9
Requires-Dist: httpx>=0.27.0
Requires-Dist: beautifulsoup4>=4.12.2
